lkmeans/__init__.py
lkmeans/clustering.py
lkmeans/data_generation/__init__.py
lkmeans/data_generation/points_generator.py
lkmeans/distance.py
lkmeans/examples/__init__.py
lkmeans/examples/experiment.py
lkmeans/examples/experiment_data.py
lkmeans/examples/main.py
lkmeans/examples/run_real_datasets.py
lkmeans/examples/utils.py
lkmeans/optimizers.py
lkmeans/report/__init__.py
lkmeans/report/decomposition.py
lkmeans/report/generate_dimension_histogram.py
lkmeans/report/metric_meter.py
lkmeans/report/plot_minkowski.py
lkmeans/tests/__init__.py
lkmeans/tests/solver_tester.py
lkmeans/tests/test_api.py
lkmeans/tests/test_cluster_assign.py
lkmeans/tests/test_optimizer.py
lkmeans-0.0.2.dist-info/LICENSE
lkmeans-0.0.2.dist-info/METADATA
lkmeans-0.0.2.dist-info/WHEEL
lkmeans-0.0.2.dist-info/RECORD
