Metadata-Version: 2.1
Name: lkmeans
Version: 0.0.2
Summary: Clustering high-dimensional data with Minkowski distance
License: LICENSE
Author: Trutnev Aleksei
Author-email: alexgiving@mail.ru
Requires-Python: >=3.10
Classifier: License :: Other/Proprietary License
Classifier: Programming Language :: Python :: 3
Classifier: Programming Language :: Python :: 3.10
Classifier: Programming Language :: Python :: 3.11
Requires-Dist: keras (==2.13.1rc0)
Requires-Dist: matplotlib (==3.6.2)
Requires-Dist: numpy (==1.24.3)
Requires-Dist: pandas (==1.5.2)
Requires-Dist: pytest (==7.2.0)
Requires-Dist: scikit-learn (==1.2.0)
Requires-Dist: scipy (==1.10.0)
Requires-Dist: tensorflow (==2.13.0rc0)
